[
    {
    "levelcode":"01",
    "name":"01",
    "level":1,
    "description":"123213213213",
    "children":[{
        "levelcode":"011",
        "name":"011",
        "level":2,
        "description":"123213213213",
        "children":[{
            "levelcode":"0111",
            "name":"0111",
            "level":3,
            "description":"123213213213"
        },{
            "levelcode":"0112",
            "name":"0112",
            "description":"123213213213",
            "level":3
        },{
            "levelcode":"0113",
            "name":"0113",
            "description":"123213213213",
            "level":3
        }]
    },{
        "levelcode":"012",
        "name":"012",
        "level":2,
        "description":"123213213213",
        "children":[{
            "levelcode":"0121",
            "name":"0121",
            "description":"123213213213",
            "level":3
        },{
            "levelcode":"0122",
            "name":"0122",
            "description":"123213213213",
            "level":3
        },{
            "levelcode":"0123",
            "name":"0123",
            "description":"123213213213",
            "level":3
        }]
    },{
        "levelcode":"013",
        "name":"013",
        "level":2,
        "children":[{
            "levelcode":"0131",
            "name":"0131",
            "description":"123213213213",
            "level":3
        },{
            "levelcode":"0132",
            "name":"0132",
            "description":"123213213213",
            "level":3
        },{
            "levelcode":"0133",
            "name":"0133",
            "description":"123213213213",
            "level":3
        }]
    }]}
]